{
    "basisSetName": "cc-pwCVTZ-DK",
    "basisSetDescription": "cc-pwCVTZ-DK",
    "basisSetElements": {
        "21": {
            "elementComponents": [
                "CC-PWCVTZ-DK"
            ]
        },
        "22": {
            "elementComponents": [
                "CC-PWCVTZ-DK"
            ]
        },
        "23": {
            "elementComponents": [
                "CC-PWCVTZ-DK"
            ]
        },
        "24": {
            "elementComponents": [
                "CC-PWCVTZ-DK"
            ]
        },
        "25": {
            "elementComponents": [
                "CC-PWCVTZ-DK"
            ]
        },
        "26": {
            "elementComponents": [
                "CC-PWCVTZ-DK"
            ]
        },
        "27": {
            "elementComponents": [
                "CC-PWCVTZ-DK"
            ]
        },
        "28": {
            "elementComponents": [
                "CC-PWCVTZ-DK"
            ]
        },
        "29": {
            "elementComponents": [
                "CC-PWCVTZ-DK"
            ]
        },
        "30": {
            "elementComponents": [
                "CC-PWCVTZ-DK"
            ]
        },
        "39": {
            "elementComponents": [
                "CC-PWCVTZ-DK"
            ]
        },
        "40": {
            "elementComponents": [
                "CC-PWCVTZ-DK"
            ]
        },
        "41": {
            "elementComponents": [
                "CC-PWCVTZ-DK"
            ]
        },
        "42": {
            "elementComponents": [
                "CC-PWCVTZ-DK"
            ]
        },
        "43": {
            "elementComponents": [
                "CC-PWCVTZ-DK"
            ]
        },
        "44": {
            "elementComponents": [
                "CC-PWCVTZ-DK"
            ]
        },
        "45": {
            "elementComponents": [
                "CC-PWCVTZ-DK"
            ]
        },
        "46": {
            "elementComponents": [
                "CC-PWCVTZ-DK"
            ]
        }
    }
}