{
    "basisSetName": "d-aug-cc-pVTZ",
    "basisSetDescription": "VTZ2PD  Valence Triple Zeta + Polarization + Diffuse",
    "basisSetElements": {
        "1": {
            "elementEntry": "D-AUG-CC-PVTZ"
        },
        "2": {
            "elementEntry": "D-AUG-CC-PVTZ"
        },
        "5": {
            "elementEntry": "D-AUG-CC-PVTZ"
        },
        "6": {
            "elementEntry": "D-AUG-CC-PVTZ"
        },
        "7": {
            "elementEntry": "D-AUG-CC-PVTZ"
        },
        "8": {
            "elementEntry": "D-AUG-CC-PVTZ"
        },
        "9": {
            "elementEntry": "D-AUG-CC-PVTZ"
        },
        "10": {
            "elementEntry": "D-AUG-CC-PVTZ"
        },
        "20": {
            "elementEntry": "CC-PVTZ"
        }
    }
}