{
    "citations": [
        {
            "Z": [
                6,
                7,
                8,
                9,
                16
            ],
            "orginal": "D. Feller, K.A. Peterson and T.D. Crawford (to be published)",
            "valid": false
        }
    ],
    "original": "\nElements                             References\n--------                             ----------\nC - F, S:       D. Feller, K.A. Peterson and T.D. Crawford (to be published)\n\n\n  ",
    "valid": true
}